futureos/__main__.py
futureos/constants.py
futureos/commands/__init__.py
futureos/commands/answer.py
futureos/commands/cat.py
futureos/commands/cd.py
futureos/commands/cls.py
futureos/commands/command.py
futureos/commands/ls.py
futureos/commands/nano.py
futureos/commands/pwd.py
futureos/commands/rm.py
futureos/init/create_collections.py
futureos/init/initialize_filesystem.py
futureos/utils/console_manager.py
futureos/utils/editor.py
futureos/utils/path_utils.py
futureos-0.3.0.dist-info/METADATA
futureos-0.3.0.dist-info/WHEEL
futureos-0.3.0.dist-info/top_level.txt
futureos-0.3.0.dist-info/RECORD
