Metadata-Version: 2.1
Name: futureos
Version: 0.3.0
Summary: First fully AI based Operating system 
Author-email: Michal Skibinski <michalskibinski109@gmail.com>
License: MIT
Project-URL: Homepage, https://github.com/miskibin/futureOS
Project-URL: Repository, https://github.com/miskibin/futureOS
Keywords: AI,Operating System,ollama,python,chromadb,langchain
Classifier: Development Status :: 4 - Beta
Classifier: Intended Audience :: Developers
Classifier: License :: OSI Approved :: MIT License
Classifier: Programming Language :: Python :: 3.10
Classifier: Programming Language :: Python :: 3.11
Classifier: Programming Language :: Python :: 3.12
Classifier: Programming Language :: Python :: 3.13
Classifier: Operating System :: OS Independent
Requires-Python: >=3.10
Requires-Dist: chromadb >=0.5.18
Requires-Dist: keyboard >=0.13.5
Requires-Dist: langchain-community >=0.3.5
Requires-Dist: langchain-ollama >=0.2.0
Requires-Dist: langchain >=0.3.7
Requires-Dist: loguru >=0.7.2
Requires-Dist: ollama >=0.3.3
Requires-Dist: pytest >=8.3.3
Requires-Dist: rich >=13.9.4
Requires-Dist: windows-curses >=2.4.0 ; platform_system == "Windows"
